{
  "topmeldung90": "Video zeigt: Zirkus-Tiger springt auf Zuschauertribüne",
  "news90_link": "https://www.servustv.com/aktuelles/v/aa3yde188t9dagv458e3/",
  "news90_title": "Video zeigt: Zirkus-Tiger springt auf Zuschauertribüne | Nachrichten in 90 Sekunden",
  "google_headlines": [
    "Abschiedsgeschenk und letzte Finte: Warum Orban jetzt Ukraine-Milliarden frei gibt - Kurier",
    "ORF-Mitarbeiterin gibt erstes TV-Interview in der Causa Weißmann: „Wenn man es sehen will, sieht man es“ - Salzburger Nachrichten",
    "Erpressermail gegen Hipp seit Donnerstag bekannt – fünf Gläser gefunden, eines im Umlauf - Der Standard"
  ],
  "ticker90": "Russland: Zirkus-Tiger springt in Publikum | Salzburg: Details zu Bus-Unfall | Ö: OMV holt Öl aus Notreserve"
}
